dhtmlparser/__init__.py
dhtmlparser/quoter.py
dhtmlparser/specialdict.py
dhtmlparser/htmlelement/__init__.py
dhtmlparser/htmlelement/html_element.py
dhtmlparser/htmlelement/html_parser.py
dhtmlparser/htmlelement/html_query.py
dhtmlparser/htmlelement/shared.py
pyDHTMLParser-2.2.3.dist-info/LICENSE.txt
pyDHTMLParser-2.2.3.dist-info/METADATA
pyDHTMLParser-2.2.3.dist-info/WHEEL
pyDHTMLParser-2.2.3.dist-info/top_level.txt
pyDHTMLParser-2.2.3.dist-info/RECORD
